training_doctor/__init__.py
training_doctor/diagnosis.py
training_doctor/doctor.py
training_doctor/detectors/__init__.py
training_doctor/detectors/base.py
training_doctor/detectors/instability.py
training_doctor/detectors/learning_rate.py
training_doctor/detectors/overfitting.py
training_doctor/detectors/plateau.py
training_doctor/integrations/__init__.py
training_doctor/integrations/accelerate.py
training_doctor/integrations/huggingface.py
training_doctor/integrations/lightning.py
training_doctor/loaders/__init__.py
training_doctor/loaders/base.py
training_doctor/loaders/csv.py
training_doctor/loaders/tensorboard.py
training_doctor/loaders/wandb.py
training_doctor/metrics/__init__.py
training_doctor/metrics/store.py
training_doctor/metrics/types.py
training_doctor/reporters/__init__.py
training_doctor/reporters/console.py
training_doctor-0.1.0.dist-info/licenses/LICENSE
training_doctor-0.1.0.dist-info/METADATA
training_doctor-0.1.0.dist-info/WHEEL
training_doctor-0.1.0.dist-info/top_level.txt
training_doctor-0.1.0.dist-info/RECORD
