Metadata-Version: 2.4
Name: training-doctor
Version: 0.1.0
Summary: A framework-agnostic library for monitoring deep learning training runs and diagnosing issues
Author: Training Doctor Contributors
License: MIT
Project-URL: Homepage, https://github.com/SalahAlHaismawi/training-doctor
Project-URL: Documentation, https://github.com/SalahAlHaismawi/training-doctor#readme
Project-URL: Repository, https://github.com/SalahAlHaismawi/training-doctor
Project-URL: Issues, https://github.com/SalahAlHaismawi/training-doctor/issues
Keywords: machine-learning,deep-learning,training,monitoring,diagnostics,llm,pytorch,transformers
Classifier: Development Status :: 3 - Alpha
Classifier: Intended Audience :: Developers
Classifier: Intended Audience :: Science/Research
Classifier: License :: OSI Approved :: MIT License
Classifier: Operating System :: OS Independent
Classifier: Programming Language :: Python :: 3
Classifier: Programming Language :: Python :: 3.8
Classifier: Programming Language :: Python :: 3.9
Classifier: Programming Language :: Python :: 3.10
Classifier: Programming Language :: Python :: 3.11
Classifier: Programming Language :: Python :: 3.12
Classifier: Topic :: Scientific/Engineering :: Artificial Intelligence
Requires-Python: >=3.8
License-File: LICENSE
Provides-Extra: tensorboard
Requires-Dist: tensorboard>=2.0; extra == "tensorboard"
Provides-Extra: wandb
Requires-Dist: wandb>=0.12; extra == "wandb"
Provides-Extra: transformers
Requires-Dist: transformers>=4.0; extra == "transformers"
Provides-Extra: lightning
Requires-Dist: pytorch-lightning>=1.0; extra == "lightning"
Provides-Extra: accelerate
Requires-Dist: accelerate>=0.12; extra == "accelerate"
Provides-Extra: all
Requires-Dist: tensorboard>=2.0; extra == "all"
Requires-Dist: wandb>=0.12; extra == "all"
Requires-Dist: transformers>=4.0; extra == "all"
Requires-Dist: pytorch-lightning>=1.0; extra == "all"
Requires-Dist: accelerate>=0.12; extra == "all"
Provides-Extra: dev
Requires-Dist: pytest>=7.0; extra == "dev"
Requires-Dist: pytest-cov>=4.0; extra == "dev"
Requires-Dist: black>=23.0; extra == "dev"
Requires-Dist: ruff>=0.1; extra == "dev"
Requires-Dist: mypy>=1.0; extra == "dev"
Dynamic: license-file
